auto_pydantic_cache/__init__.py
auto_pydantic_cache/py.typed
auto_pydantic_cache-1.1.1.dist-info/WHEEL
auto_pydantic_cache-1.1.1.dist-info/METADATA
auto_pydantic_cache-1.1.1.dist-info/RECORD
